[
    {
        "BlockType": "PAGE",
        "Geometry": {
            "BoundingBox": {
                "Height": 1,
                "Left": 0,
                "Top": 0,
                "Width": 1
            },
            "Polygon": [
                {
                    "X": 7.401155244224356e-8,
                    "Y": 5.649038925525929e-8
                },
                {
                    "X": 1,
                    "Y": 0
                },
                {
                    "X": 1,
                    "Y": 1
                },
                {
                    "X": 0,
                    "Y": 1
                }
            ]
        },
        "Id": "aee11035-e0e0-40a2-9df6-595eefa2a12d",
        "Relationships": [
            {
                "Ids": [
                    "e1c12768-4fbf-4803-b6f0-6479e1d25d87",
                    "9bd9b569-ea21-4d6b-afbc-8ff8c3a482c9",
                    "c22eb720-1696-4c20-8899-8623d54368e1",
                    "d8878872-2c2b-48b6-ba19-459661e85203",
                    "18f3beaa-fdb0-4541-8f66-33288f27de6d",
                    "9b75d376-3ac3-459e-af29-e061b6e3d852",
                    "b234fad5-2b93-42a2-a483-8a90b4a2c93c",
                    "ab98bdd0-c5e8-4254-a3f0-9754bc6c7212",
                    "c70ce54e-f863-4599-98b1-6ed47718111d",
                    "e30b9e0b-240d-4f0d-98d2-a218f03c5f28",
                    "3f06a0b5-0e03-4023-98e5-02c75f6cd6b3",
                    "e90e9223-75b2-4ce6-be6b-9ea053b3d88d",
                    "f81ccea9-4cef-4297-a59d-79a7b12fcfd5",
                    "b5b1d959-5e2a-40f0-b00d-2987d1b88596",
                    "949a97ef-93f3-436a-94fd-50fdcd3c7c75",
                    "d5a415e4-c404-41ad-99f1-54981a0c93d9",
                    "97c9bad4-5422-4563-90ea-03e450d8f02e",
                    "3e2b46a6-80e0-420a-bcdf-cc2dc0ec576c",
                    "bd86142d-f8aa-4304-8de0-c97879ecb9e4",
                    "eba5a960-7547-4fbf-8f39-6b631be2f672",
                    "2b6465ad-386c-4530-8407-c71719ff5c81",
                    "d51521ee-8aa6-437c-a564-fce6bcba4251"
                ],
                "Type": "CHILD"
            }
        ]
    },
    {
        "BlockType": "LINE",
        "Confidence": 99.90702056884766,
        "Geometry": {
            "BoundingBox": {
                "Height": 0.026882929727435112,
                "Left": 0.45646920800209045,
                "Top": 0.09439455717802048,
                "Width": 0.0863417237997055
            },
            "Polygon": [
                {
                    "X": 0.45648297667503357,
                    "Y": 0.09461011737585068
                },
                {
                    "X": 0.5428109169006348,
                    "Y": 0.09439455717802048
                },
                {
                    "X": 0.5427955389022827,
                    "Y": 0.12106195092201233
                },
                {
                    "X": 0.45646920800209045,
                    "Y": 0.12127748876810074
                }
            ]
        },
        "Id": "e1c12768-4fbf-4803-b6f0-6479e1d25d87",
        "Relationships": [
            {
                "Ids": [
                    "755bb2b8-e9e3-4d81-b73c-2c5d13cbd4a7"
                ],
                "Type": "CHILD"
            }
        ],
        "Text": "VPIP"
    },
    {
        "BlockType": "LINE",
        "Confidence": 99.91494750976562,
        "Geometry": {
            "BoundingBox": {
                "Height": 0.021269379183650017,
                "Left": 0.04172184318304062,
                "Top": 0.18650123476982117,
                "Width": 0.11736201494932175
            },
            "Polygon": [
                {
                    "X": 0.0417264848947525,
                    "Y": 0.1867942065000534
                },
                {
                    "X": 0.15908385813236237,
                    "Y": 0.18650123476982117
                },
                {
                    "X": 0.1590774655342102,
                    "Y": 0.20747767388820648
                },
                {
                    "X": 0.04172184318304062,
                    "Y": 0.20777061581611633
                }
            ]
        },
        "Id": "9bd9b569-ea21-4d6b-afbc-8ff8c3a482c9",
        "Relationships": [
            {
                "Ids": [
                    "2cea57b0-50d2-413b-807c-304b2f5f2208"
                ],
                "Type": "CHILD"
            }
        ],
        "Text": "KEATING"
    },
    {
        "BlockType": "LINE",
        "Confidence": 99.74617767333984,
        "Geometry": {
            "BoundingBox": {
                "Height": 0.02269081398844719,
                "Left": 0.8991132378578186,
                "Top": 0.1865789294242859,
                "Width": 0.06532953679561615
            },
            "Polygon": [
                {
                    "X": 0.8991320133209229,
                    "Y": 0.18674196302890778
                },
                {
                    "X": 0.964442789554596,
                    "Y": 0.1865789294242859
                },
                {
                    "X": 0.9644230008125305,
                    "Y": 0.2091067135334015
                },
                {
                    "X": 0.8991132378578186,
                    "Y": 0.20926974713802338
                }
            ]
        },
        "Id": "c22eb720-1696-4c20-8899-8623d54368e1",
        "Relationships": [
            {
                "Ids": [
                    "704f3e12-5d55-4585-b3b2-3fc0a92aca6d"
                ],
                "Type": "CHILD"
            }
        ],
        "Text": "57%"
    },
    {
        "BlockType": "LINE",
        "Confidence": 99.93035125732422,
        "Geometry": {
            "BoundingBox": {
                "Height": 0.023432645946741104,
                "Left": 0.041328467428684235,
                "Top": 0.253133088350296,
                "Width": 0.12895208597183228
            },
            "Polygon": [
                {
                    "X": 0.04133357107639313,
                    "Y": 0.25345492362976074
                },
                {
                    "X": 0.1702805459499359,
                    "Y": 0.253133088350296
                },
                {
                    "X": 0.1702733188867569,
                    "Y": 0.2762439250946045
                },
                {
                    "X": 0.041328467428684235,
                    "Y": 0.2765657305717468
                }
            ]
        },
        "Id": "d8878872-2c2b-48b6-ba19-459661e85203",
        "Relationships": [
            {
                "Ids": [
                    "c79c8ad9-0f27-4a49-b89a-797272d01a33"
                ],
                "Type": "CHILD"
            }
        ],
        "Text": "CHARLES"
    },
    {
        "BlockType": "LINE",
        "Confidence": 99.83104705810547,
        "Geometry": {
            "BoundingBox": {
                "Height": 0.022302119061350822,
                "Left": 0.8995556235313416,
                "Top": 0.25402799248695374,
                "Width": 0.0643840953707695
            },
            "Polygon": [
                {
                    "X": 0.8995741009712219,
                    "Y": 0.2541886270046234
                },
                {
                    "X": 0.9639397263526917,
                    "Y": 0.25402799248695374
                },
                {
                    "X": 0.9639202952384949,
                    "Y": 0.27616944909095764
                },
                {
                    "X": 0.8995556235313416,
                    "Y": 0.2763301134109497
                }
            ]
        },
        "Id": "18f3beaa-fdb0-4541-8f66-33288f27de6d",
        "Relationships": [
            {
                "Ids": [
                    "1229113e-5bab-4433-be27-2941ab8fb113"
                ],
                "Type": "CHILD"
            }
        ],
        "Text": "52%"
    },
    {
        "BlockType": "LINE",
        "Confidence": 99.97399139404297,
        "Geometry": {
            "BoundingBox": {
                "Height": 0.02185979299247265,
                "Left": 0.03999565541744232,
                "Top": 0.3213133215904236,
                "Width": 0.07781712710857391
            },
            "Polygon": [
                {
                    "X": 0.040000420063734055,
                    "Y": 0.3215075135231018
                },
                {
                    "X": 0.11781278252601624,
                    "Y": 0.3213133215904236
                },
                {
                    "X": 0.1178068146109581,
                    "Y": 0.34297895431518555
                },
                {
                    "X": 0.03999565541744232,
                    "Y": 0.3431731164455414
                }
            ]
        },
        "Id": "9b75d376-3ac3-459e-af29-e061b6e3d852",
        "Relationships": [
            {
                "Ids": [
                    "03d52899-2221-475f-99b6-70dd48283370"
                ],
                "Type": "CHILD"
            }
        ],
        "Text": "ANDY"
    },
    {
        "BlockType": "LINE",
        "Confidence": 99.94342041015625,
        "Geometry": {
            "BoundingBox": {
                "Height": 0.022018518298864365,
                "Left": 0.8998415470123291,
                "Top": 0.32191914319992065,
                "Width": 0.06368252635002136
            },
            "Polygon": [
                {
                    "X": 0.8998597264289856,
                    "Y": 0.32207798957824707
                },
                {
                    "X": 0.9635240435600281,
                    "Y": 0.32191914319992065
                },
                {
                    "X": 0.9635048508644104,
                    "Y": 0.3437787890434265
                },
                {
                    "X": 0.8998415470123291,
                    "Y": 0.34393763542175293
                }
            ]
        },
        "Id": "b234fad5-2b93-42a2-a483-8a90b4a2c93c",
        "Relationships": [
            {
                "Ids": [
                    "ae4535dd-7a6b-47ee-9add-9371580d35c5"
                ],
                "Type": "CHILD"
            }
        ],
        "Text": "48%"
    },
    {
        "BlockType": "LINE",
        "Confidence": 98.37886810302734,
        "Geometry": {
            "BoundingBox": {
                "Height": 0.02201256901025772,
                "Left": 0.04126085340976715,
                "Top": 0.38908207416534424,
                "Width": 0.14990906417369843
            },
            "Polygon": [
                {
                    "X": 0.04126563295722008,
                    "Y": 0.3894560635089874
                },
                {
                    "X": 0.19116991758346558,
                    "Y": 0.38908207416534424
                },
                {
                    "X": 0.1911628246307373,
                    "Y": 0.4107206463813782
                },
                {
                    "X": 0.04126085340976715,
                    "Y": 0.41109463572502136
                }
            ]
        },
        "Id": "ab98bdd0-c5e8-4254-a3f0-9754bc6c7212",
        "Relationships": [
            {
                "Ids": [
                    "6b7ca358-23c1-4efe-bf59-b6f36d69fb0a"
                ],
                "Type": "CHILD"
            }
        ],
        "Text": "SANTHOSH"
    },
    {
        "BlockType": "LINE",
        "Confidence": 99.50922393798828,
        "Geometry": {
            "BoundingBox": {
                "Height": 0.021862944588065147,
                "Left": 0.9013168215751648,
                "Top": 0.38966381549835205,
                "Width": 0.06045118719339371
            },
            "Polygon": [
                {
                    "X": 0.9013348817825317,
                    "Y": 0.3898146152496338
                },
                {
                    "X": 0.9617679715156555,
                    "Y": 0.38966381549835205
                },
                {
                    "X": 0.9617489576339722,
                    "Y": 0.4113759994506836
                },
                {
                    "X": 0.9013168215751648,
                    "Y": 0.41152676939964294
                }
            ]
        },
        "Id": "c70ce54e-f863-4599-98b1-6ed47718111d",
        "Relationships": [
            {
                "Ids": [
                    "8d4ddab0-bbaf-4866-8805-790eaa39e4dd"
                ],
                "Type": "CHILD"
            }
        ],
        "Text": "48%"
    },
    {
        "BlockType": "LINE",
        "Confidence": 23.028757095336914,
        "Geometry": {
            "BoundingBox": {
                "Height": 0.027673739939928055,
                "Left": 0.9814859628677368,
                "Top": 0.3810412287712097,
                "Width": 0.01812940277159214
            },
            "Polygon": [
                {
                    "X": 0.981510579586029,
                    "Y": 0.38108640909194946
                },
                {
                    "X": 0.9996153712272644,
                    "Y": 0.3810412287712097
                },
                {
                    "X": 0.9995903968811035,
                    "Y": 0.4086697995662689
                },
                {
                    "X": 0.9814859628677368,
                    "Y": 0.40871497988700867
                }
            ]
        },
        "Id": "e30b9e0b-240d-4f0d-98d2-a218f03c5f28",
        "Relationships": [
            {
                "Ids": [
                    "26b20b0d-61f5-4cde-ac1d-6673fc283ca6"
                ],
                "Type": "CHILD"
            }
        ],
        "Text": "THE"
    },
    {
        "BlockType": "LINE",
        "Confidence": 98.98490142822266,
        "Geometry": {
            "BoundingBox": {
                "Height": 0.020561883226037025,
                "Left": 0.04008428379893303,
                "Top": 0.45751914381980896,
                "Width": 0.0510857030749321
            },
            "Polygon": [
                {
                    "X": 0.04008878394961357,
                    "Y": 0.45764657855033875
                },
                {
                    "X": 0.09116999059915543,
                    "Y": 0.45751914381980896
                },
                {
                    "X": 0.09116475284099579,
                    "Y": 0.47795361280441284
                },
                {
                    "X": 0.04008428379893303,
                    "Y": 0.4780810475349426
                }
            ]
        },
        "Id": "3f06a0b5-0e03-4023-98e5-02c75f6cd6b3",
        "Relationships": [
            {
                "Ids": [
                    "950e142d-a5b1-41a3-96d7-887c2e022a92"
                ],
                "Type": "CHILD"
            }
        ],
        "Text": "J.R."
    },
    {
        "BlockType": "LINE",
        "Confidence": 99.89329528808594,
        "Geometry": {
            "BoundingBox": {
                "Height": 0.02114463783800602,
                "Left": 0.8998982906341553,
                "Top": 0.45728975534439087,
                "Width": 0.06236782670021057
            },
            "Polygon": [
                {
                    "X": 0.8999157547950745,
                    "Y": 0.45744529366493225
                },
                {
                    "X": 0.9622661471366882,
                    "Y": 0.45728975534439087
                },
                {
                    "X": 0.9622477293014526,
                    "Y": 0.47827884554862976
                },
                {
                    "X": 0.8998982906341553,
                    "Y": 0.47843438386917114
                }
            ]
        },
        "Id": "e90e9223-75b2-4ce6-be6b-9ea053b3d88d",
        "Relationships": [
            {
                "Ids": [
                    "47d9852f-1fb4-4417-9168-1c029e716c7d"
                ],
                "Type": "CHILD"
            }
        ],
        "Text": "47%"
    },
    {
        "BlockType": "LINE",
        "Confidence": 99.90843200683594,
        "Geometry": {
            "BoundingBox": {
                "Height": 0.02259097993373871,
                "Left": 0.04037639871239662,
                "Top": 0.5237340331077576,
                "Width": 0.09735521674156189
            },
            "Polygon": [
                {
                    "X": 0.04038132354617119,
                    "Y": 0.5239768624305725
                },
                {
                    "X": 0.1377316117286682,
                    "Y": 0.5237340331077576
                },
                {
                    "X": 0.13772514462471008,
                    "Y": 0.5460821986198425
                },
                {
                    "X": 0.04037639871239662,
                    "Y": 0.5463250279426575
                }
            ]
        },
        "Id": "f81ccea9-4cef-4297-a59d-79a7b12fcfd5",
        "Relationships": [
            {
                "Ids": [
                    "5d1d1acc-1e13-4d03-ab79-29746c540138"
                ],
                "Type": "CHILD"
            }
        ],
        "Text": "HANKS"
    },
    {
        "BlockType": "LINE",
        "Confidence": 99.91026306152344,
        "Geometry": {
            "BoundingBox": {
                "Height": 0.02150643989443779,
                "Left": 0.8999925255775452,
                "Top": 0.5246976613998413,
                "Width": 0.06280980259180069
            },
            "Polygon": [
                {
                    "X": 0.9000102877616882,
                    "Y": 0.524854302406311
                },
                {
                    "X": 0.9628023505210876,
                    "Y": 0.5246976613998413
                },
                {
                    "X": 0.9627835750579834,
                    "Y": 0.5460475087165833
                },
                {
                    "X": 0.8999925255775452,
                    "Y": 0.5462040901184082
                }
            ]
        },
        "Id": "b5b1d959-5e2a-40f0-b00d-2987d1b88596",
        "Relationships": [
            {
                "Ids": [
                    "a4ea8879-9664-40bb-8ec8-06fe3c59bf10"
                ],
                "Type": "CHILD"
            }
        ],
        "Text": "45%"
    },
    {
        "BlockType": "LINE",
        "Confidence": 99.86164093017578,
        "Geometry": {
            "BoundingBox": {
                "Height": 0.022681502625346184,
                "Left": 0.040377840399742126,
                "Top": 0.5917700529098511,
                "Width": 0.11969996243715286
            },
            "Polygon": [
                {
                    "X": 0.04038276895880699,
                    "Y": 0.5920685529708862
                },
                {
                    "X": 0.1600777953863144,
                    "Y": 0.5917700529098511
                },
                {
                    "X": 0.16007095575332642,
                    "Y": 0.6141530871391296
                },
                {
                    "X": 0.040377840399742126,
                    "Y": 0.6144515872001648
                }
            ]
        },
        "Id": "949a97ef-93f3-436a-94fd-50fdcd3c7c75",
        "Relationships": [
            {
                "Ids": [
                    "719b9806-9bbd-428f-ab3c-1e564526b0b9"
                ],
                "Type": "CHILD"
            }
        ],
        "Text": "SASHIMI"
    },
    {
        "BlockType": "LINE",
        "Confidence": 99.9522476196289,
        "Geometry": {
            "BoundingBox": {
                "Height": 0.02169472724199295,
                "Left": 0.8995919227600098,
                "Top": 0.592185378074646,
                "Width": 0.06425722688436508
            },
            "Polygon": [
                {
                    "X": 0.8996098637580872,
                    "Y": 0.5923455357551575
                },
                {
                    "X": 0.9638491868972778,
                    "Y": 0.592185378074646
                },
                {
                    "X": 0.9638302326202393,
                    "Y": 0.6137198805809021
                },
                {
                    "X": 0.8995919227600098,
                    "Y": 0.6138800978660583
                }
            ]
        },
        "Id": "d5a415e4-c404-41ad-99f1-54981a0c93d9",
        "Relationships": [
            {
                "Ids": [
                    "816b4eb5-0699-4e95-96d9-44a3ffde800b"
                ],
                "Type": "CHILD"
            }
        ],
        "Text": "44%"
    },
    {
        "BlockType": "LINE",
        "Confidence": 99.92389678955078,
        "Geometry": {
            "BoundingBox": {
                "Height": 0.022928958758711815,
                "Left": 0.04053964465856552,
                "Top": 0.6588675379753113,
                "Width": 0.16681137681007385
            },
            "Polygon": [
                {
                    "X": 0.04054460674524307,
                    "Y": 0.659283459186554
                },
                {
                    "X": 0.20735102891921997,
                    "Y": 0.6588675379753113
                },
                {
                    "X": 0.20734338462352753,
                    "Y": 0.6813806295394897
                },
                {
                    "X": 0.04053964465856552,
                    "Y": 0.6817964911460876
                }
            ]
        },
        "Id": "97c9bad4-5422-4563-90ea-03e450d8f02e",
        "Relationships": [
            {
                "Ids": [
                    "3cb7acff-0873-4c33-9b9e-5303bc64d351"
                ],
                "Type": "CHILD"
            }
        ],
        "Text": "PROFESSOR"
    },
    {
        "BlockType": "LINE",
        "Confidence": 99.85453033447266,
        "Geometry": {
            "BoundingBox": {
                "Height": 0.02206631936132908,
                "Left": 0.8994547724723816,
                "Top": 0.6596049666404724,
                "Width": 0.06479466706514359
            },
            "Polygon": [
                {
                    "X": 0.8994730114936829,
                    "Y": 0.6597664952278137
                },
                {
                    "X": 0.9642494916915894,
                    "Y": 0.6596049666404724
                },
                {
                    "X": 0.9642302393913269,
                    "Y": 0.681509792804718
                },
                {
                    "X": 0.8994547724723816,
                    "Y": 0.6816713213920593
                }
            ]
        },
        "Id": "3e2b46a6-80e0-420a-bcdf-cc2dc0ec576c",
        "Relationships": [
            {
                "Ids": [
                    "a248ab3a-53bf-41b6-85ba-6d8046bf4965"
                ],
                "Type": "CHILD"
            }
        ],
        "Text": "41%"
    },
    {
        "BlockType": "LINE",
        "Confidence": 99.92414855957031,
        "Geometry": {
            "BoundingBox": {
                "Height": 0.021725814789533615,
                "Left": 0.04091481491923332,
                "Top": 0.7270686030387878,
                "Width": 0.17533187568187714
            },
            "Polygon": [
                {
                    "X": 0.04091951251029968,
                    "Y": 0.7275056838989258
                },
                {
                    "X": 0.21624669432640076,
                    "Y": 0.7270686030387878
                },
                {
                    "X": 0.216239333152771,
                    "Y": 0.748357355594635
                },
                {
                    "X": 0.04091481491923332,
                    "Y": 0.748794436454773
                }
            ]
        },
        "Id": "bd86142d-f8aa-4304-8de0-c97879ecb9e4",
        "Relationships": [
            {
                "Ids": [
                    "a30846d9-92ac-48d5-a4a3-dce9cb8de0fb",
                    "ed7d26a4-d0b4-4bdf-b16c-6b1e8348afc6"
                ],
                "Type": "CHILD"
            }
        ],
        "Text": "NIK AIRBALL"
    },
    {
        "BlockType": "LINE",
        "Confidence": 99.62422943115234,
        "Geometry": {
            "BoundingBox": {
                "Height": 0.021761072799563408,
                "Left": 0.9002612829208374,
                "Top": 0.72746741771698,
                "Width": 0.06337033957242966
            },
            "Polygon": [
                {
                    "X": 0.9002792835235596,
                    "Y": 0.7276253700256348
                },
                {
                    "X": 0.9636316299438477,
                    "Y": 0.72746741771698
                },
                {
                    "X": 0.9636126756668091,
                    "Y": 0.7490705847740173
                },
                {
                    "X": 0.9002612829208374,
                    "Y": 0.7492285370826721
                }
            ]
        },
        "Id": "eba5a960-7547-4fbf-8f39-6b631be2f672",
        "Relationships": [
            {
                "Ids": [
                    "fe14a806-b468-4d9d-a3ac-25bbf2d93dc1"
                ],
                "Type": "CHILD"
            }
        ],
        "Text": "36%"
    },
    {
        "BlockType": "LINE",
        "Confidence": 99.01795196533203,
        "Geometry": {
            "BoundingBox": {
                "Height": 0.02283899113535881,
                "Left": 0.03934215009212494,
                "Top": 0.794277548789978,
                "Width": 0.1142643466591835
            },
            "Polygon": [
                {
                    "X": 0.039347101002931595,
                    "Y": 0.7945622801780701
                },
                {
                    "X": 0.15360648930072784,
                    "Y": 0.794277548789978
                },
                {
                    "X": 0.15359970927238464,
                    "Y": 0.8168317675590515
                },
                {
                    "X": 0.03934215009212494,
                    "Y": 0.8171164989471436
                }
            ]
        },
        "Id": "2b6465ad-386c-4530-8407-c71719ff5c81",
        "Relationships": [
            {
                "Ids": [
                    "a69ce145-2687-4cb2-a2dc-463f83d46add"
                ],
                "Type": "CHILD"
            }
        ],
        "Text": "JBOOGS"
    },
    {
        "BlockType": "LINE",
        "Confidence": 99.802001953125,
        "Geometry": {
            "BoundingBox": {
                "Height": 0.021733516827225685,
                "Left": 0.8998907804489136,
                "Top": 0.7949448823928833,
                "Width": 0.06396359950304031
            },
            "Polygon": [
                {
                    "X": 0.8999087810516357,
                    "Y": 0.7951042652130127
                },
                {
                    "X": 0.9638543725013733,
                    "Y": 0.7949448823928833
                },
                {
                    "X": 0.9638354182243347,
                    "Y": 0.8165190815925598
                },
                {
                    "X": 0.8998907804489136,
                    "Y": 0.8166784048080444
                }
            ]
        },
        "Id": "d51521ee-8aa6-437c-a564-fce6bcba4251",
        "Relationships": [
            {
                "Ids": [
                    "5f6f6925-06b5-4157-8b50-a5a349d611e9"
                ],
                "Type": "CHILD"
            }
        ],
        "Text": "26%"
    },
    {
        "BlockType": "WORD",
        "Confidence": 99.90702056884766,
        "Geometry": {
            "BoundingBox": {
                "Height": 0.026882929727435112,
                "Left": 0.45646920800209045,
                "Top": 0.09439455717802048,
                "Width": 0.0863417237997055
            },
            "Polygon": [
                {
                    "X": 0.45648297667503357,
                    "Y": 0.09461011737585068
                },
                {
                    "X": 0.5428109169006348,
                    "Y": 0.09439455717802048
                },
                {
                    "X": 0.5427955389022827,
                    "Y": 0.12106195092201233
                },
                {
                    "X": 0.45646920800209045,
                    "Y": 0.12127748876810074
                }
            ]
        },
        "Id": "755bb2b8-e9e3-4d81-b73c-2c5d13cbd4a7",
        "Text": "VPIP",
        "TextType": "PRINTED"
    },
    {
        "BlockType": "WORD",
        "Confidence": 99.91494750976562,
        "Geometry": {
            "BoundingBox": {
                "Height": 0.021269379183650017,
                "Left": 0.04172184318304062,
                "Top": 0.18650123476982117,
                "Width": 0.11736201494932175
            },
            "Polygon": [
                {
                    "X": 0.0417264848947525,
                    "Y": 0.1867942065000534
                },
                {
                    "X": 0.15908385813236237,
                    "Y": 0.18650123476982117
                },
                {
                    "X": 0.1590774655342102,
                    "Y": 0.20747767388820648
                },
                {
                    "X": 0.04172184318304062,
                    "Y": 0.20777061581611633
                }
            ]
        },
        "Id": "2cea57b0-50d2-413b-807c-304b2f5f2208",
        "Text": "KEATING",
        "TextType": "PRINTED"
    },
    {
        "BlockType": "WORD",
        "Confidence": 99.74617767333984,
        "Geometry": {
            "BoundingBox": {
                "Height": 0.02269081398844719,
                "Left": 0.8991132378578186,
                "Top": 0.1865789294242859,
                "Width": 0.06532953679561615
            },
            "Polygon": [
                {
                    "X": 0.8991320133209229,
                    "Y": 0.18674196302890778
                },
                {
                    "X": 0.964442789554596,
                    "Y": 0.1865789294242859
                },
                {
                    "X": 0.9644230008125305,
                    "Y": 0.2091067135334015
                },
                {
                    "X": 0.8991132378578186,
                    "Y": 0.20926974713802338
                }
            ]
        },
        "Id": "704f3e12-5d55-4585-b3b2-3fc0a92aca6d",
        "Text": "57%",
        "TextType": "PRINTED"
    },
    {
        "BlockType": "WORD",
        "Confidence": 99.93035125732422,
        "Geometry": {
            "BoundingBox": {
                "Height": 0.023432645946741104,
                "Left": 0.041328467428684235,
                "Top": 0.253133088350296,
                "Width": 0.12895208597183228
            },
            "Polygon": [
                {
                    "X": 0.04133357107639313,
                    "Y": 0.25345492362976074
                },
                {
                    "X": 0.1702805459499359,
                    "Y": 0.253133088350296
                },
                {
                    "X": 0.1702733188867569,
                    "Y": 0.2762439250946045
                },
                {
                    "X": 0.041328467428684235,
                    "Y": 0.2765657305717468
                }
            ]
        },
        "Id": "c79c8ad9-0f27-4a49-b89a-797272d01a33",
        "Text": "CHARLES",
        "TextType": "PRINTED"
    },
    {
        "BlockType": "WORD",
        "Confidence": 99.83104705810547,
        "Geometry": {
            "BoundingBox": {
                "Height": 0.022302119061350822,
                "Left": 0.8995556235313416,
                "Top": 0.25402799248695374,
                "Width": 0.0643840953707695
            },
            "Polygon": [
                {
                    "X": 0.8995741009712219,
                    "Y": 0.2541886270046234
                },
                {
                    "X": 0.9639397263526917,
                    "Y": 0.25402799248695374
                },
                {
                    "X": 0.9639202952384949,
                    "Y": 0.27616944909095764
                },
                {
                    "X": 0.8995556235313416,
                    "Y": 0.2763301134109497
                }
            ]
        },
        "Id": "1229113e-5bab-4433-be27-2941ab8fb113",
        "Text": "52%",
        "TextType": "PRINTED"
    },
    {
        "BlockType": "WORD",
        "Confidence": 99.97399139404297,
        "Geometry": {
            "BoundingBox": {
                "Height": 0.02185979299247265,
                "Left": 0.03999565541744232,
                "Top": 0.3213133215904236,
                "Width": 0.07781712710857391
            },
            "Polygon": [
                {
                    "X": 0.040000420063734055,
                    "Y": 0.3215075135231018
                },
                {
                    "X": 0.11781278252601624,
                    "Y": 0.3213133215904236
                },
                {
                    "X": 0.1178068146109581,
                    "Y": 0.34297895431518555
                },
                {
                    "X": 0.03999565541744232,
                    "Y": 0.3431731164455414
                }
            ]
        },
        "Id": "03d52899-2221-475f-99b6-70dd48283370",
        "Text": "ANDY",
        "TextType": "PRINTED"
    },
    {
        "BlockType": "WORD",
        "Confidence": 99.94342041015625,
        "Geometry": {
            "BoundingBox": {
                "Height": 0.022018518298864365,
                "Left": 0.8998415470123291,
                "Top": 0.32191914319992065,
                "Width": 0.06368252635002136
            },
            "Polygon": [
                {
                    "X": 0.8998597264289856,
                    "Y": 0.32207798957824707
                },
                {
                    "X": 0.9635240435600281,
                    "Y": 0.32191914319992065
                },
                {
                    "X": 0.9635048508644104,
                    "Y": 0.3437787890434265
                },
                {
                    "X": 0.8998415470123291,
                    "Y": 0.34393763542175293
                }
            ]
        },
        "Id": "ae4535dd-7a6b-47ee-9add-9371580d35c5",
        "Text": "48%",
        "TextType": "PRINTED"
    },
    {
        "BlockType": "WORD",
        "Confidence": 98.37886810302734,
        "Geometry": {
            "BoundingBox": {
                "Height": 0.02201256901025772,
                "Left": 0.04126085340976715,
                "Top": 0.38908207416534424,
                "Width": 0.14990906417369843
            },
            "Polygon": [
                {
                    "X": 0.04126563295722008,
                    "Y": 0.3894560635089874
                },
                {
                    "X": 0.19116991758346558,
                    "Y": 0.38908207416534424
                },
                {
                    "X": 0.1911628246307373,
                    "Y": 0.4107206463813782
                },
                {
                    "X": 0.04126085340976715,
                    "Y": 0.41109463572502136
                }
            ]
        },
        "Id": "6b7ca358-23c1-4efe-bf59-b6f36d69fb0a",
        "Text": "SANTHOSH",
        "TextType": "PRINTED"
    },
    {
        "BlockType": "WORD",
        "Confidence": 99.50922393798828,
        "Geometry": {
            "BoundingBox": {
                "Height": 0.021862944588065147,
                "Left": 0.9013168215751648,
                "Top": 0.38966381549835205,
                "Width": 0.06045118719339371
            },
            "Polygon": [
                {
                    "X": 0.9013348817825317,
                    "Y": 0.3898146152496338
                },
                {
                    "X": 0.9617679715156555,
                    "Y": 0.38966381549835205
                },
                {
                    "X": 0.9617489576339722,
                    "Y": 0.4113759994506836
                },
                {
                    "X": 0.9013168215751648,
                    "Y": 0.41152676939964294
                }
            ]
        },
        "Id": "8d4ddab0-bbaf-4866-8805-790eaa39e4dd",
        "Text": "48%",
        "TextType": "PRINTED"
    },
    {
        "BlockType": "WORD",
        "Confidence": 23.028757095336914,
        "Geometry": {
            "BoundingBox": {
                "Height": 0.027673739939928055,
                "Left": 0.9814859628677368,
                "Top": 0.3810412287712097,
                "Width": 0.01812940277159214
            },
            "Polygon": [
                {
                    "X": 0.981510579586029,
                    "Y": 0.38108640909194946
                },
                {
                    "X": 0.9996153712272644,
                    "Y": 0.3810412287712097
                },
                {
                    "X": 0.9995903968811035,
                    "Y": 0.4086697995662689
                },
                {
                    "X": 0.9814859628677368,
                    "Y": 0.40871497988700867
                }
            ]
        },
        "Id": "26b20b0d-61f5-4cde-ac1d-6673fc283ca6",
        "Text": "THE",
        "TextType": "PRINTED"
    },
    {
        "BlockType": "WORD",
        "Confidence": 98.98490142822266,
        "Geometry": {
            "BoundingBox": {
                "Height": 0.020561883226037025,
                "Left": 0.04008428379893303,
                "Top": 0.45751914381980896,
                "Width": 0.0510857030749321
            },
            "Polygon": [
                {
                    "X": 0.04008878394961357,
                    "Y": 0.45764657855033875
                },
                {
                    "X": 0.09116999059915543,
                    "Y": 0.45751914381980896
                },
                {
                    "X": 0.09116475284099579,
                    "Y": 0.47795361280441284
                },
                {
                    "X": 0.04008428379893303,
                    "Y": 0.4780810475349426
                }
            ]
        },
        "Id": "950e142d-a5b1-41a3-96d7-887c2e022a92",
        "Text": "J.R.",
        "TextType": "PRINTED"
    },
    {
        "BlockType": "WORD",
        "Confidence": 99.89329528808594,
        "Geometry": {
            "BoundingBox": {
                "Height": 0.02114463783800602,
                "Left": 0.8998982906341553,
                "Top": 0.45728975534439087,
                "Width": 0.06236782670021057
            },
            "Polygon": [
                {
                    "X": 0.8999157547950745,
                    "Y": 0.45744529366493225
                },
                {
                    "X": 0.9622661471366882,
                    "Y": 0.45728975534439087
                },
                {
                    "X": 0.9622477293014526,
                    "Y": 0.47827884554862976
                },
                {
                    "X": 0.8998982906341553,
                    "Y": 0.47843438386917114
                }
            ]
        },
        "Id": "47d9852f-1fb4-4417-9168-1c029e716c7d",
        "Text": "47%",
        "TextType": "PRINTED"
    },
    {
        "BlockType": "WORD",
        "Confidence": 99.90843200683594,
        "Geometry": {
            "BoundingBox": {
                "Height": 0.02259097993373871,
                "Left": 0.04037639871239662,
                "Top": 0.5237340331077576,
                "Width": 0.09735521674156189
            },
            "Polygon": [
                {
                    "X": 0.04038132354617119,
                    "Y": 0.5239768624305725
                },
                {
                    "X": 0.1377316117286682,
                    "Y": 0.5237340331077576
                },
                {
                    "X": 0.13772514462471008,
                    "Y": 0.5460821986198425
                },
                {
                    "X": 0.04037639871239662,
                    "Y": 0.5463250279426575
                }
            ]
        },
        "Id": "5d1d1acc-1e13-4d03-ab79-29746c540138",
        "Text": "HANKS",
        "TextType": "PRINTED"
    },
    {
        "BlockType": "WORD",
        "Confidence": 99.91026306152344,
        "Geometry": {
            "BoundingBox": {
                "Height": 0.02150643989443779,
                "Left": 0.8999925255775452,
                "Top": 0.5246976613998413,
                "Width": 0.06280980259180069
            },
            "Polygon": [
                {
                    "X": 0.9000102877616882,
                    "Y": 0.524854302406311
                },
                {
                    "X": 0.9628023505210876,
                    "Y": 0.5246976613998413
                },
                {
                    "X": 0.9627835750579834,
                    "Y": 0.5460475087165833
                },
                {
                    "X": 0.8999925255775452,
                    "Y": 0.5462040901184082
                }
            ]
        },
        "Id": "a4ea8879-9664-40bb-8ec8-06fe3c59bf10",
        "Text": "45%",
        "TextType": "PRINTED"
    },
    {
        "BlockType": "WORD",
        "Confidence": 99.86164093017578,
        "Geometry": {
            "BoundingBox": {
                "Height": 0.022681502625346184,
                "Left": 0.040377840399742126,
                "Top": 0.5917700529098511,
                "Width": 0.11969996243715286
            },
            "Polygon": [
                {
                    "X": 0.04038276895880699,
                    "Y": 0.5920685529708862
                },
                {
                    "X": 0.1600777953863144,
                    "Y": 0.5917700529098511
                },
                {
                    "X": 0.16007095575332642,
                    "Y": 0.6141530871391296
                },
                {
                    "X": 0.040377840399742126,
                    "Y": 0.6144515872001648
                }
            ]
        },
        "Id": "719b9806-9bbd-428f-ab3c-1e564526b0b9",
        "Text": "SASHIMI",
        "TextType": "PRINTED"
    },
    {
        "BlockType": "WORD",
        "Confidence": 99.9522476196289,
        "Geometry": {
            "BoundingBox": {
                "Height": 0.02169472724199295,
                "Left": 0.8995919227600098,
                "Top": 0.592185378074646,
                "Width": 0.06425722688436508
            },
            "Polygon": [
                {
                    "X": 0.8996098637580872,
                    "Y": 0.5923455357551575
                },
                {
                    "X": 0.9638491868972778,
                    "Y": 0.592185378074646
                },
                {
                    "X": 0.9638302326202393,
                    "Y": 0.6137198805809021
                },
                {
                    "X": 0.8995919227600098,
                    "Y": 0.6138800978660583
                }
            ]
        },
        "Id": "816b4eb5-0699-4e95-96d9-44a3ffde800b",
        "Text": "44%",
        "TextType": "PRINTED"
    },
    {
        "BlockType": "WORD",
        "Confidence": 99.92389678955078,
        "Geometry": {
            "BoundingBox": {
                "Height": 0.022928958758711815,
                "Left": 0.04053964465856552,
                "Top": 0.6588675379753113,
                "Width": 0.16681137681007385
            },
            "Polygon": [
                {
                    "X": 0.04054460674524307,
                    "Y": 0.659283459186554
                },
                {
                    "X": 0.20735102891921997,
                    "Y": 0.6588675379753113
                },
                {
                    "X": 0.20734338462352753,
                    "Y": 0.6813806295394897
                },
                {
                    "X": 0.04053964465856552,
                    "Y": 0.6817964911460876
                }
            ]
        },
        "Id": "3cb7acff-0873-4c33-9b9e-5303bc64d351",
        "Text": "PROFESSOR",
        "TextType": "PRINTED"
    },
    {
        "BlockType": "WORD",
        "Confidence": 99.85453033447266,
        "Geometry": {
            "BoundingBox": {
                "Height": 0.02206631936132908,
                "Left": 0.8994547724723816,
                "Top": 0.6596049666404724,
                "Width": 0.06479466706514359
            },
            "Polygon": [
                {
                    "X": 0.8994730114936829,
                    "Y": 0.6597664952278137
                },
                {
                    "X": 0.9642494916915894,
                    "Y": 0.6596049666404724
                },
                {
                    "X": 0.9642302393913269,
                    "Y": 0.681509792804718
                },
                {
                    "X": 0.8994547724723816,
                    "Y": 0.6816713213920593
                }
            ]
        },
        "Id": "a248ab3a-53bf-41b6-85ba-6d8046bf4965",
        "Text": "41%",
        "TextType": "PRINTED"
    },
    {
        "BlockType": "WORD",
        "Confidence": 99.9179458618164,
        "Geometry": {
            "BoundingBox": {
                "Height": 0.021019291132688522,
                "Left": 0.04091490060091019,
                "Top": 0.7273821830749512,
                "Width": 0.04955006390810013
            },
            "Polygon": [
                {
                    "X": 0.04091951251029968,
                    "Y": 0.7275056838989258
                },
                {
                    "X": 0.09046496450901031,
                    "Y": 0.7273821830749512
                },
                {
                    "X": 0.09045961499214172,
                    "Y": 0.7482779622077942
                },
                {
                    "X": 0.04091490060091019,
                    "Y": 0.7484014630317688
                }
            ]
        },
        "Id": "a30846d9-92ac-48d5-a4a3-dce9cb8de0fb",
        "Text": "NIK",
        "TextType": "PRINTED"
    },
    {
        "BlockType": "WORD",
        "Confidence": 99.93035125732422,
        "Geometry": {
            "BoundingBox": {
                "Height": 0.021088367328047752,
                "Left": 0.09622158855199814,
                "Top": 0.7275682091712952,
                "Width": 0.12002492696046829
            },
            "Polygon": [
                {
                    "X": 0.0962269976735115,
                    "Y": 0.7278673648834229
                },
                {
                    "X": 0.21624651551246643,
                    "Y": 0.7275682091712952
                },
                {
                    "X": 0.216239333152771,
                    "Y": 0.748357355594635
                },
                {
                    "X": 0.09622158855199814,
                    "Y": 0.7486565709114075
                }
            ]
        },
        "Id": "ed7d26a4-d0b4-4bdf-b16c-6b1e8348afc6",
        "Text": "AIRBALL",
        "TextType": "PRINTED"
    },
    {
        "BlockType": "WORD",
        "Confidence": 99.62422943115234,
        "Geometry": {
            "BoundingBox": {
                "Height": 0.021761072799563408,
                "Left": 0.9002612829208374,
                "Top": 0.72746741771698,
                "Width": 0.06337033957242966
            },
            "Polygon": [
                {
                    "X": 0.9002792835235596,
                    "Y": 0.7276253700256348
                },
                {
                    "X": 0.9636316299438477,
                    "Y": 0.72746741771698
                },
                {
                    "X": 0.9636126756668091,
                    "Y": 0.7490705847740173
                },
                {
                    "X": 0.9002612829208374,
                    "Y": 0.7492285370826721
                }
            ]
        },
        "Id": "fe14a806-b468-4d9d-a3ac-25bbf2d93dc1",
        "Text": "36%",
        "TextType": "PRINTED"
    },
    {
        "BlockType": "WORD",
        "Confidence": 99.01795196533203,
        "Geometry": {
            "BoundingBox": {
                "Height": 0.02283899113535881,
                "Left": 0.03934215009212494,
                "Top": 0.794277548789978,
                "Width": 0.1142643466591835
            },
            "Polygon": [
                {
                    "X": 0.039347101002931595,
                    "Y": 0.7945622801780701
                },
                {
                    "X": 0.15360648930072784,
                    "Y": 0.794277548789978
                },
                {
                    "X": 0.15359970927238464,
                    "Y": 0.8168317675590515
                },
                {
                    "X": 0.03934215009212494,
                    "Y": 0.8171164989471436
                }
            ]
        },
        "Id": "a69ce145-2687-4cb2-a2dc-463f83d46add",
        "Text": "JBOOGS",
        "TextType": "PRINTED"
    },
    {
        "BlockType": "WORD",
        "Confidence": 99.802001953125,
        "Geometry": {
            "BoundingBox": {
                "Height": 0.021733516827225685,
                "Left": 0.8998907804489136,
                "Top": 0.7949448823928833,
                "Width": 0.06396359950304031
            },
            "Polygon": [
                {
                    "X": 0.8999087810516357,
                    "Y": 0.7951042652130127
                },
                {
                    "X": 0.9638543725013733,
                    "Y": 0.7949448823928833
                },
                {
                    "X": 0.9638354182243347,
                    "Y": 0.8165190815925598
                },
                {
                    "X": 0.8998907804489136,
                    "Y": 0.8166784048080444
                }
            ]
        },
        "Id": "5f6f6925-06b5-4157-8b50-a5a349d611e9",
        "Text": "26%",
        "TextType": "PRINTED"
    }
]