[
    {
        "BlockType": "PAGE",
        "Geometry": {
            "BoundingBox": {
                "Height": 0.9439866542816162,
                "Left": 0.002412246074527502,
                "Top": 0,
                "Width": 0.9975877404212952
            },
            "Polygon": [
                {
                    "X": 0.002412246074527502,
                    "Y": 0
                },
                {
                    "X": 1,
                    "Y": 0
                },
                {
                    "X": 1,
                    "Y": 0.9421812891960144
                },
                {
                    "X": 0.002579702064394951,
                    "Y": 0.9439866542816162
                }
            ]
        },
        "Id": "da1cf5bd-e2cd-4184-96e9-c3ff7e1d3643",
        "Relationships": [
            {
                "Ids": [
                    "412e79f8-e7ca-4ef6-8297-0e2b2031c857",
                    "c343a429-c7ef-4840-abb4-e3d36ece3622",
                    "04be5e4b-44ce-4142-bbc1-b03b5412ae11",
                    "4c9f27eb-557d-4a23-b99e-3069766a24f4",
                    "82023fa2-4692-4944-bb70-0c11efcbdbb8",
                    "18ea4432-1156-4588-bacb-a27734f52573",
                    "f537e12f-d375-4b73-b344-57e2dbd4eff6",
                    "a088c08d-0bc3-4709-9075-34a68f465125",
                    "c3d35066-7243-42cd-90f3-33e2f2570bd2",
                    "40148f7a-62b3-4ff2-bc11-363f5b711c4a",
                    "a86f60af-c888-46e0-b06a-8ab742eabf05",
                    "b34d4467-f66c-4264-8df8-60ae3046f7eb",
                    "3ca35195-ca01-4570-8e71-0b3fe5b4148f",
                    "33fa41a7-535b-4b29-a585-7252333997bb",
                    "6fc5894e-6e21-49f1-af2d-b9dcdae55e22",
                    "3bd0058c-79cc-4c4c-989d-ced0aa09dd21",
                    "1bc41d63-d0b0-49f0-b61e-6d82a47b6d22",
                    "51fe4d94-702f-4592-b1fa-7da606be5d1b",
                    "a7b7fba8-d3ef-4bd3-931a-0cc0128de356",
                    "7998c6a3-f74c-4dc8-b936-b41614605637",
                    "9d775101-237b-4e9c-8833-2a09caaf31e9"
                ],
                "Type": "CHILD"
            }
        ]
    },
    {
        "BlockType": "LINE",
        "Confidence": 99.91592407226562,
        "Geometry": {
            "BoundingBox": {
                "Height": 0.029863391071558,
                "Left": 0.3450673520565033,
                "Top": 0.12062035501003265,
                "Width": 0.3097715377807617
            },
            "Polygon": [
                {
                    "X": 0.3450694978237152,
                    "Y": 0.12141362577676773
                },
                {
                    "X": 0.6548389196395874,
                    "Y": 0.12062035501003265
                },
                {
                    "X": 0.6548301577568054,
                    "Y": 0.14969874918460846
                },
                {
                    "X": 0.3450673520565033,
                    "Y": 0.15048374235630035
                }
            ]
        },
        "Id": "412e79f8-e7ca-4ef6-8297-0e2b2031c857",
        "Relationships": [
            {
                "Ids": [
                    "ab50dfad-8f6e-4070-b975-6047d6021e9d",
                    "f8b11fc4-be59-4909-b0de-7fe17159b823"
                ],
                "Type": "CHILD"
            }
        ],
        "Text": "PRE-FLOP RAISE"
    },
    {
        "BlockType": "LINE",
        "Confidence": 99.95549774169922,
        "Geometry": {
            "BoundingBox": {
                "Height": 0.02267499640583992,
                "Left": 0.04039669781923294,
                "Top": 0.2163415104150772,
                "Width": 0.0760822519659996
            },
            "Polygon": [
                {
                    "X": 0.04039669781923294,
                    "Y": 0.2165297567844391
                },
                {
                    "X": 0.11647683382034302,
                    "Y": 0.2163415104150772
                },
                {
                    "X": 0.11647894978523254,
                    "Y": 0.2388298213481903
                },
                {
                    "X": 0.04040006175637245,
                    "Y": 0.23901650309562683
                }
            ]
        },
        "Id": "c343a429-c7ef-4840-abb4-e3d36ece3622",
        "Relationships": [
            {
                "Ids": [
                    "e2fd75f0-64b0-4976-bdfb-627cf007d30d"
                ],
                "Type": "CHILD"
            }
        ],
        "Text": "DGAF"
    },
    {
        "BlockType": "LINE",
        "Confidence": 99.92881774902344,
        "Geometry": {
            "BoundingBox": {
                "Height": 0.02325795590877533,
                "Left": 0.899716854095459,
                "Top": 0.21656490862369537,
                "Width": 0.06509291380643845
            },
            "Polygon": [
                {
                    "X": 0.8997279405593872,
                    "Y": 0.21672581136226654
                },
                {
                    "X": 0.964809775352478,
                    "Y": 0.21656490862369537
                },
                {
                    "X": 0.9647975564002991,
                    "Y": 0.23966334760189056
                },
                {
                    "X": 0.899716854095459,
                    "Y": 0.2398228645324707
                }
            ]
        },
        "Id": "04be5e4b-44ce-4142-bbc1-b03b5412ae11",
        "Relationships": [
            {
                "Ids": [
                    "216dd6cd-2147-4b35-8fb9-30eda01b7a78"
                ],
                "Type": "CHILD"
            }
        ],
        "Text": "30%"
    },
    {
        "BlockType": "LINE",
        "Confidence": 99.86243438720703,
        "Geometry": {
            "BoundingBox": {
                "Height": 0.02497021108865738,
                "Left": 0.0403546467423439,
                "Top": 0.2826850414276123,
                "Width": 0.13970039784908295
            },
            "Polygon": [
                {
                    "X": 0.0403546467423439,
                    "Y": 0.2830221951007843
                },
                {
                    "X": 0.18005387485027313,
                    "Y": 0.2826850414276123
                },
                {
                    "X": 0.18005503714084625,
                    "Y": 0.3073212504386902
                },
                {
                    "X": 0.04035833477973938,
                    "Y": 0.3076552450656891
                }
            ]
        },
        "Id": "4c9f27eb-557d-4a23-b99e-3069766a24f4",
        "Relationships": [
            {
                "Ids": [
                    "82ba72d4-6b1e-4b08-9f7e-32be4100a2a8"
                ],
                "Type": "CHILD"
            }
        ],
        "Text": "RAMPAGE"
    },
    {
        "BlockType": "LINE",
        "Confidence": 99.87309265136719,
        "Geometry": {
            "BoundingBox": {
                "Height": 0.022578079253435135,
                "Left": 0.8997756838798523,
                "Top": 0.28446248173713684,
                "Width": 0.06508921831846237
            },
            "Polygon": [
                {
                    "X": 0.8997864723205566,
                    "Y": 0.2846193313598633
                },
                {
                    "X": 0.9648649096488953,
                    "Y": 0.28446248173713684
                },
                {
                    "X": 0.9648531079292297,
                    "Y": 0.3068850636482239
                },
                {
                    "X": 0.8997756838798523,
                    "Y": 0.3070405423641205
                }
            ]
        },
        "Id": "82023fa2-4692-4944-bb70-0c11efcbdbb8",
        "Relationships": [
            {
                "Ids": [
                    "cc029561-da42-4f31-9362-a04fd042f062"
                ],
                "Type": "CHILD"
            }
        ],
        "Text": "25%"
    },
    {
        "BlockType": "LINE",
        "Confidence": 99.89405059814453,
        "Geometry": {
            "BoundingBox": {
                "Height": 0.023506980389356613,
                "Left": 0.04056720435619354,
                "Top": 0.3509782552719116,
                "Width": 0.18573324382305145
            },
            "Polygon": [
                {
                    "X": 0.04056720435619354,
                    "Y": 0.35141488909721375
                },
                {
                    "X": 0.22630015015602112,
                    "Y": 0.3509782552719116
                },
                {
                    "X": 0.2263004630804062,
                    "Y": 0.3740525543689728
                },
                {
                    "X": 0.04057065397500992,
                    "Y": 0.3744852542877197
                }
            ]
        },
        "Id": "18ea4432-1156-4588-bacb-a27734f52573",
        "Relationships": [
            {
                "Ids": [
                    "b58730d0-e59d-4074-9066-252f9bf39a76",
                    "cfdce3c9-e7e5-4936-be68-b82710bcce68"
                ],
                "Type": "CHILD"
            }
        ],
        "Text": "CRAZY DREW"
    },
    {
        "BlockType": "LINE",
        "Confidence": 99.79069519042969,
        "Geometry": {
            "BoundingBox": {
                "Height": 0.022154884412884712,
                "Left": 0.8999002575874329,
                "Top": 0.35233163833618164,
                "Width": 0.06450914591550827
            },
            "Polygon": [
                {
                    "X": 0.8999108076095581,
                    "Y": 0.3524830937385559
                },
                {
                    "X": 0.9644094109535217,
                    "Y": 0.35233163833618164
                },
                {
                    "X": 0.9643977880477905,
                    "Y": 0.3743363916873932
                },
                {
                    "X": 0.8999002575874329,
                    "Y": 0.3744865357875824
                }
            ]
        },
        "Id": "f537e12f-d375-4b73-b344-57e2dbd4eff6",
        "Relationships": [
            {
                "Ids": [
                    "1df299ae-ab11-48cd-b211-f48b5a3f0bee"
                ],
                "Type": "CHILD"
            }
        ],
        "Text": "20%"
    },
    {
        "BlockType": "LINE",
        "Confidence": 99.94644927978516,
        "Geometry": {
            "BoundingBox": {
                "Height": 0.023418592289090157,
                "Left": 0.040041450411081314,
                "Top": 0.4188142418861389,
                "Width": 0.07006073743104935
            },
            "Polygon": [
                {
                    "X": 0.040041450411081314,
                    "Y": 0.4189746081829071
                },
                {
                    "X": 0.1100998967885971,
                    "Y": 0.4188142418861389
                },
                {
                    "X": 0.11010219156742096,
                    "Y": 0.4420740008354187
                },
                {
                    "X": 0.040044937282800674,
                    "Y": 0.4422328472137451
                }
            ]
        },
        "Id": "a088c08d-0bc3-4709-9075-34a68f465125",
        "Relationships": [
            {
                "Ids": [
                    "b7606205-aac9-499d-9b28-0def4793c16b"
                ],
                "Type": "CHILD"
            }
        ],
        "Text": "NICK"
    },
    {
        "BlockType": "LINE",
        "Confidence": 99.961181640625,
        "Geometry": {
            "BoundingBox": {
                "Height": 0.02284795418381691,
                "Left": 0.9009459018707275,
                "Top": 0.41939887404441833,
                "Width": 0.06394555419683456
            },
            "Polygon": [
                {
                    "X": 0.9009568095207214,
                    "Y": 0.41954505443573
                },
                {
                    "X": 0.9648914933204651,
                    "Y": 0.41939887404441833
                },
                {
                    "X": 0.9648795127868652,
                    "Y": 0.44210195541381836
                },
                {
                    "X": 0.9009459018707275,
                    "Y": 0.44224682450294495
                }
            ]
        },
        "Id": "c3d35066-7243-42cd-90f3-33e2f2570bd2",
        "Relationships": [
            {
                "Ids": [
                    "4a3b66d2-8884-444c-8b5f-a2df4bb4e6c7"
                ],
                "Type": "CHILD"
            }
        ],
        "Text": "14%"
    },
    {
        "BlockType": "LINE",
        "Confidence": 99.95044708251953,
        "Geometry": {
            "BoundingBox": {
                "Height": 0.021519336849451065,
                "Left": 0.040748003870248795,
                "Top": 0.4871576428413391,
                "Width": 0.040342047810554504
            },
            "Polygon": [
                {
                    "X": 0.040748003870248795,
                    "Y": 0.4872474670410156
                },
                {
                    "X": 0.08108748495578766,
                    "Y": 0.4871576428413391
                },
                {
                    "X": 0.081090047955513,
                    "Y": 0.5085879564285278
                },
                {
                    "X": 0.04075120389461517,
                    "Y": 0.5086770057678223
                }
            ]
        },
        "Id": "40148f7a-62b3-4ff2-bc11-363f5b711c4a",
        "Relationships": [
            {
                "Ids": [
                    "47c5c4f2-e342-4328-90e7-2761cdcf15be"
                ],
                "Type": "CHILD"
            }
        ],
        "Text": "DK"
    },
    {
        "BlockType": "LINE",
        "Confidence": 99.91349792480469,
        "Geometry": {
            "BoundingBox": {
                "Height": 0.022693080827593803,
                "Left": 0.9006170034408569,
                "Top": 0.4872561991214752,
                "Width": 0.06411666423082352
            },
            "Polygon": [
                {
                    "X": 0.900627851486206,
                    "Y": 0.48739880323410034
                },
                {
                    "X": 0.9647336602210999,
                    "Y": 0.4872561991214752
                },
                {
                    "X": 0.9647217988967896,
                    "Y": 0.5098080039024353
                },
                {
                    "X": 0.9006170034408569,
                    "Y": 0.509949266910553
                }
            ]
        },
        "Id": "a86f60af-c888-46e0-b06a-8ab742eabf05",
        "Relationships": [
            {
                "Ids": [
                    "1d90873c-4d5c-4c41-989e-5e921198b3c0"
                ],
                "Type": "CHILD"
            }
        ],
        "Text": "12%"
    },
    {
        "BlockType": "LINE",
        "Confidence": 99.97563934326172,
        "Geometry": {
            "BoundingBox": {
                "Height": 0.022064663469791412,
                "Left": 0.04104761779308319,
                "Top": 0.5547930002212524,
                "Width": 0.07316429167985916
            },
            "Polygon": [
                {
                    "X": 0.04104761779308319,
                    "Y": 0.5549513101577759
                },
                {
                    "X": 0.11420981585979462,
                    "Y": 0.5547930002212524
                },
                {
                    "X": 0.11421190947294235,
                    "Y": 0.5767008066177368
                },
                {
                    "X": 0.04105088487267494,
                    "Y": 0.5768576264381409
                }
            ]
        },
        "Id": "b34d4467-f66c-4264-8df8-60ae3046f7eb",
        "Relationships": [
            {
                "Ids": [
                    "5bf07e13-8edb-45bb-8187-4779b290659e"
                ],
                "Type": "CHILD"
            }
        ],
        "Text": "FRED"
    },
    {
        "BlockType": "LINE",
        "Confidence": 99.97491455078125,
        "Geometry": {
            "BoundingBox": {
                "Height": 0.023219842463731766,
                "Left": 0.9009563326835632,
                "Top": 0.5544626116752625,
                "Width": 0.06372009217739105
            },
            "Polygon": [
                {
                    "X": 0.9009674191474915,
                    "Y": 0.5546003580093384
                },
                {
                    "X": 0.9646764397621155,
                    "Y": 0.5544626116752625
                },
                {
                    "X": 0.9646642804145813,
                    "Y": 0.5775460004806519
                },
                {
                    "X": 0.9009563326835632,
                    "Y": 0.5776824355125427
                }
            ]
        },
        "Id": "3ca35195-ca01-4570-8e71-0b3fe5b4148f",
        "Relationships": [
            {
                "Ids": [
                    "355969b0-4cf9-434c-9a5d-4f3bad29f11e"
                ],
                "Type": "CHILD"
            }
        ],
        "Text": "10%"
    },
    {
        "BlockType": "LINE",
        "Confidence": 99.9441146850586,
        "Geometry": {
            "BoundingBox": {
                "Height": 0.02231493592262268,
                "Left": 0.04025565832853317,
                "Top": 0.6223545074462891,
                "Width": 0.07157742977142334
            },
            "Polygon": [
                {
                    "X": 0.04025565832853317,
                    "Y": 0.6225049495697021
                },
                {
                    "X": 0.111830934882164,
                    "Y": 0.6223545074462891
                },
                {
                    "X": 0.11183308809995651,
                    "Y": 0.6445204019546509
                },
                {
                    "X": 0.0402589775621891,
                    "Y": 0.6446694135665894
                }
            ]
        },
        "Id": "33fa41a7-535b-4b29-a585-7252333997bb",
        "Relationships": [
            {
                "Ids": [
                    "ed8c9d88-2733-47bd-84f3-847a025e6374"
                ],
                "Type": "CHILD"
            }
        ],
        "Text": "LULU"
    },
    {
        "BlockType": "LINE",
        "Confidence": 99.9078140258789,
        "Geometry": {
            "BoundingBox": {
                "Height": 0.023816082626581192,
                "Left": 0.9175830483436584,
                "Top": 0.621654212474823,
                "Width": 0.048026397824287415
            },
            "Polygon": [
                {
                    "X": 0.9175947308540344,
                    "Y": 0.6217551231384277
                },
                {
                    "X": 0.9656094312667847,
                    "Y": 0.621654212474823
                },
                {
                    "X": 0.9655969142913818,
                    "Y": 0.6453704833984375
                },
                {
                    "X": 0.9175830483436584,
                    "Y": 0.6454703211784363
                }
            ]
        },
        "Id": "6fc5894e-6e21-49f1-af2d-b9dcdae55e22",
        "Relationships": [
            {
                "Ids": [
                    "406ca1e3-a0e4-4030-a29a-c02fce542beb"
                ],
                "Type": "CHILD"
            }
        ],
        "Text": "9%"
    },
    {
        "BlockType": "LINE",
        "Confidence": 99.94876861572266,
        "Geometry": {
            "BoundingBox": {
                "Height": 0.023442856967449188,
                "Left": 0.03989062085747719,
                "Top": 0.6891514658927917,
                "Width": 0.07530452311038971
            },
            "Polygon": [
                {
                    "X": 0.03989062085747719,
                    "Y": 0.6893051862716675
                },
                {
                    "X": 0.11519293487071991,
                    "Y": 0.6891514658927917
                },
                {
                    "X": 0.1151951402425766,
                    "Y": 0.7124422788619995
                },
                {
                    "X": 0.03989411145448685,
                    "Y": 0.7125943303108215
                }
            ]
        },
        "Id": "3bd0058c-79cc-4c4c-989d-ced0aa09dd21",
        "Relationships": [
            {
                "Ids": [
                    "4a99d94e-6e55-4de3-bffc-389158869243"
                ],
                "Type": "CHILD"
            }
        ],
        "Text": "NEAL"
    },
    {
        "BlockType": "LINE",
        "Confidence": 99.87632751464844,
        "Geometry": {
            "BoundingBox": {
                "Height": 0.023502489551901817,
                "Left": 0.915650486946106,
                "Top": 0.6899284720420837,
                "Width": 0.04817110300064087
            },
            "Polygon": [
                {
                    "X": 0.9156619906425476,
                    "Y": 0.6900266408920288
                },
                {
                    "X": 0.9638215899467468,
                    "Y": 0.6899284720420837
                },
                {
                    "X": 0.9638092517852783,
                    "Y": 0.713333785533905
                },
                {
                    "X": 0.915650486946106,
                    "Y": 0.7134309411048889
                }
            ]
        },
        "Id": "1bc41d63-d0b0-49f0-b61e-6d82a47b6d22",
        "Relationships": [
            {
                "Ids": [
                    "53701db6-46e9-4d97-93d8-ea160e1e9eba"
                ],
                "Type": "CHILD"
            }
        ],
        "Text": "6%"
    },
    {
        "BlockType": "LINE",
        "Confidence": 99.84471893310547,
        "Geometry": {
            "BoundingBox": {
                "Height": 0.023483803495764732,
                "Left": 0.040284089744091034,
                "Top": 0.7569553256034851,
                "Width": 0.08713126927614212
            },
            "Polygon": [
                {
                    "X": 0.040284089744091034,
                    "Y": 0.7571277618408203
                },
                {
                    "X": 0.12741336226463318,
                    "Y": 0.7569553256034851
                },
                {
                    "X": 0.12741535902023315,
                    "Y": 0.7802686095237732
                },
                {
                    "X": 0.04028758034110069,
                    "Y": 0.7804391384124756
                }
            ]
        },
        "Id": "51fe4d94-702f-4592-b1fa-7da606be5d1b",
        "Relationships": [
            {
                "Ids": [
                    "be83142f-e979-4920-b2d5-4f8e2e4fdf48"
                ],
                "Type": "CHILD"
            }
        ],
        "Text": "NIKOS"
    },
    {
        "BlockType": "LINE",
        "Confidence": 99.71063995361328,
        "Geometry": {
            "BoundingBox": {
                "Height": 0.02298501878976822,
                "Left": 0.9171431064605713,
                "Top": 0.7571859359741211,
                "Width": 0.04866519942879677
            },
            "Polygon": [
                {
                    "X": 0.9171543717384338,
                    "Y": 0.7572821378707886
                },
                {
                    "X": 0.9658082723617554,
                    "Y": 0.7571859359741211
                },
                {
                    "X": 0.965796172618866,
                    "Y": 0.7800757884979248
                },
                {
                    "X": 0.9171431064605713,
                    "Y": 0.7801709771156311
                }
            ]
        },
        "Id": "a7b7fba8-d3ef-4bd3-931a-0cc0128de356",
        "Relationships": [
            {
                "Ids": [
                    "d69373bb-3824-4d6d-b546-40d3d40dec2d"
                ],
                "Type": "CHILD"
            }
        ],
        "Text": "4%"
    },
    {
        "BlockType": "LINE",
        "Confidence": 20.346712112426758,
        "Geometry": {
            "BoundingBox": {
                "Height": 0.046435922384262085,
                "Left": 0.9817333817481995,
                "Top": 0.769607424736023,
                "Width": 0.018071450293064117
            },
            "Polygon": [
                {
                    "X": 0.9817584156990051,
                    "Y": 0.7696428894996643
                },
                {
                    "X": 0.9998047947883606,
                    "Y": 0.769607424736023
                },
                {
                    "X": 0.9997791647911072,
                    "Y": 0.8160086274147034
                },
                {
                    "X": 0.9817333817481995,
                    "Y": 0.8160433173179626
                }
            ]
        },
        "Id": "7998c6a3-f74c-4dc8-b936-b41614605637",
        "Relationships": [
            {
                "Ids": [
                    "87f101ce-d870-4508-8965-5dad46466be7"
                ],
                "Type": "CHILD"
            }
        ],
        "Text": "1"
    },
    {
        "BlockType": "LINE",
        "Confidence": 23.694299697875977,
        "Geometry": {
            "BoundingBox": {
                "Height": 0.022322269156575203,
                "Left": 0.9827743768692017,
                "Top": 0.8711729049682617,
                "Width": 0.01722564548254013
            },
            "Polygon": [
                {
                    "X": 0.9827864170074463,
                    "Y": 0.8712056279182434
                },
                {
                    "X": 1,
                    "Y": 0.8711729049682617
                },
                {
                    "X": 1,
                    "Y": 0.8934627771377563
                },
                {
                    "X": 0.9827743768692017,
                    "Y": 0.8934951424598694
                }
            ]
        },
        "Id": "9d775101-237b-4e9c-8833-2a09caaf31e9",
        "Relationships": [
            {
                "Ids": [
                    "53d4e1d5-9c1b-4509-a7cf-b766e26a9dfc"
                ],
                "Type": "CHILD"
            }
        ],
        "Text": "las"
    },
    {
        "BlockType": "WORD",
        "Confidence": 99.859375,
        "Geometry": {
            "BoundingBox": {
                "Height": 0.029431188479065895,
                "Left": 0.3450673818588257,
                "Top": 0.12093906104564667,
                "Width": 0.1853184551000595
            },
            "Polygon": [
                {
                    "X": 0.3450694978237152,
                    "Y": 0.12141362577676773
                },
                {
                    "X": 0.5303858518600464,
                    "Y": 0.12093906104564667
                },
                {
                    "X": 0.5303797721862793,
                    "Y": 0.1499006152153015
                },
                {
                    "X": 0.3450673818588257,
                    "Y": 0.150370255112648
                }
            ]
        },
        "Id": "ab50dfad-8f6e-4070-b975-6047d6021e9d",
        "Text": "PRE-FLOP",
        "TextType": "PRINTED"
    },
    {
        "BlockType": "WORD",
        "Confidence": 99.97246551513672,
        "Geometry": {
            "BoundingBox": {
                "Height": 0.028719451278448105,
                "Left": 0.5434623956680298,
                "Top": 0.12126152217388153,
                "Width": 0.11137630045413971
            },
            "Polygon": [
                {
                    "X": 0.5434685945510864,
                    "Y": 0.1215466558933258
                },
                {
                    "X": 0.6548386812210083,
                    "Y": 0.12126152217388153
                },
                {
                    "X": 0.6548301577568054,
                    "Y": 0.14969874918460846
                },
                {
                    "X": 0.5434623956680298,
                    "Y": 0.14998097717761993
                }
            ]
        },
        "Id": "f8b11fc4-be59-4909-b0de-7fe17159b823",
        "Text": "RAISE",
        "TextType": "PRINTED"
    },
    {
        "BlockType": "WORD",
        "Confidence": 99.95549774169922,
        "Geometry": {
            "BoundingBox": {
                "Height": 0.02267499640583992,
                "Left": 0.04039669781923294,
                "Top": 0.2163415104150772,
                "Width": 0.0760822519659996
            },
            "Polygon": [
                {
                    "X": 0.04039669781923294,
                    "Y": 0.2165297567844391
                },
                {
                    "X": 0.11647683382034302,
                    "Y": 0.2163415104150772
                },
                {
                    "X": 0.11647894978523254,
                    "Y": 0.2388298213481903
                },
                {
                    "X": 0.04040006175637245,
                    "Y": 0.23901650309562683
                }
            ]
        },
        "Id": "e2fd75f0-64b0-4976-bdfb-627cf007d30d",
        "Text": "DGAF",
        "TextType": "PRINTED"
    },
    {
        "BlockType": "WORD",
        "Confidence": 99.92881774902344,
        "Geometry": {
            "BoundingBox": {
                "Height": 0.02325795590877533,
                "Left": 0.899716854095459,
                "Top": 0.21656490862369537,
                "Width": 0.06509291380643845
            },
            "Polygon": [
                {
                    "X": 0.8997279405593872,
                    "Y": 0.21672581136226654
                },
                {
                    "X": 0.964809775352478,
                    "Y": 0.21656490862369537
                },
                {
                    "X": 0.9647975564002991,
                    "Y": 0.23966334760189056
                },
                {
                    "X": 0.899716854095459,
                    "Y": 0.2398228645324707
                }
            ]
        },
        "Id": "216dd6cd-2147-4b35-8fb9-30eda01b7a78",
        "Text": "30%",
        "TextType": "PRINTED"
    },
    {
        "BlockType": "WORD",
        "Confidence": 99.86243438720703,
        "Geometry": {
            "BoundingBox": {
                "Height": 0.02497021108865738,
                "Left": 0.0403546467423439,
                "Top": 0.2826850414276123,
                "Width": 0.13970039784908295
            },
            "Polygon": [
                {
                    "X": 0.0403546467423439,
                    "Y": 0.2830221951007843
                },
                {
                    "X": 0.18005387485027313,
                    "Y": 0.2826850414276123
                },
                {
                    "X": 0.18005503714084625,
                    "Y": 0.3073212504386902
                },
                {
                    "X": 0.04035833477973938,
                    "Y": 0.3076552450656891
                }
            ]
        },
        "Id": "82ba72d4-6b1e-4b08-9f7e-32be4100a2a8",
        "Text": "RAMPAGE",
        "TextType": "PRINTED"
    },
    {
        "BlockType": "WORD",
        "Confidence": 99.87309265136719,
        "Geometry": {
            "BoundingBox": {
                "Height": 0.022578079253435135,
                "Left": 0.8997756838798523,
                "Top": 0.28446248173713684,
                "Width": 0.06508921831846237
            },
            "Polygon": [
                {
                    "X": 0.8997864723205566,
                    "Y": 0.2846193313598633
                },
                {
                    "X": 0.9648649096488953,
                    "Y": 0.28446248173713684
                },
                {
                    "X": 0.9648531079292297,
                    "Y": 0.3068850636482239
                },
                {
                    "X": 0.8997756838798523,
                    "Y": 0.3070405423641205
                }
            ]
        },
        "Id": "cc029561-da42-4f31-9362-a04fd042f062",
        "Text": "25%",
        "TextType": "PRINTED"
    },
    {
        "BlockType": "WORD",
        "Confidence": 99.82379150390625,
        "Geometry": {
            "BoundingBox": {
                "Height": 0.023066816851496696,
                "Left": 0.04056720435619354,
                "Top": 0.35119664669036865,
                "Width": 0.09283164143562317
            },
            "Polygon": [
                {
                    "X": 0.04056720435619354,
                    "Y": 0.35141488909721375
                },
                {
                    "X": 0.13339698314666748,
                    "Y": 0.35119664669036865
                },
                {
                    "X": 0.1333988457918167,
                    "Y": 0.374047189950943
                },
                {
                    "X": 0.04057062044739723,
                    "Y": 0.3742634654045105
                }
            ]
        },
        "Id": "b58730d0-e59d-4074-9066-252f9bf39a76",
        "Text": "CRAZY",
        "TextType": "PRINTED"
    },
    {
        "BlockType": "WORD",
        "Confidence": 99.96431732177734,
        "Geometry": {
            "BoundingBox": {
                "Height": 0.022538719698786736,
                "Left": 0.14042094349861145,
                "Top": 0.3517138957977295,
                "Width": 0.08587950468063354
            },
            "Polygon": [
                {
                    "X": 0.14042094349861145,
                    "Y": 0.35191571712493896
                },
                {
                    "X": 0.22630015015602112,
                    "Y": 0.3517138957977295
                },
                {
                    "X": 0.2263004630804062,
                    "Y": 0.3740525543689728
                },
                {
                    "X": 0.14042265713214874,
                    "Y": 0.3742526173591614
                }
            ]
        },
        "Id": "cfdce3c9-e7e5-4936-be68-b82710bcce68",
        "Text": "DREW",
        "TextType": "PRINTED"
    },
    {
        "BlockType": "WORD",
        "Confidence": 99.79069519042969,
        "Geometry": {
            "BoundingBox": {
                "Height": 0.022154884412884712,
                "Left": 0.8999002575874329,
                "Top": 0.35233163833618164,
                "Width": 0.06450914591550827
            },
            "Polygon": [
                {
                    "X": 0.8999108076095581,
                    "Y": 0.3524830937385559
                },
                {
                    "X": 0.9644094109535217,
                    "Y": 0.35233163833618164
                },
                {
                    "X": 0.9643977880477905,
                    "Y": 0.3743363916873932
                },
                {
                    "X": 0.8999002575874329,
                    "Y": 0.3744865357875824
                }
            ]
        },
        "Id": "1df299ae-ab11-48cd-b211-f48b5a3f0bee",
        "Text": "20%",
        "TextType": "PRINTED"
    },
    {
        "BlockType": "WORD",
        "Confidence": 99.94644927978516,
        "Geometry": {
            "BoundingBox": {
                "Height": 0.023418592289090157,
                "Left": 0.040041450411081314,
                "Top": 0.4188142418861389,
                "Width": 0.07006073743104935
            },
            "Polygon": [
                {
                    "X": 0.040041450411081314,
                    "Y": 0.4189746081829071
                },
                {
                    "X": 0.1100998967885971,
                    "Y": 0.4188142418861389
                },
                {
                    "X": 0.11010219156742096,
                    "Y": 0.4420740008354187
                },
                {
                    "X": 0.040044937282800674,
                    "Y": 0.4422328472137451
                }
            ]
        },
        "Id": "b7606205-aac9-499d-9b28-0def4793c16b",
        "Text": "NICK",
        "TextType": "PRINTED"
    },
    {
        "BlockType": "WORD",
        "Confidence": 99.961181640625,
        "Geometry": {
            "BoundingBox": {
                "Height": 0.02284795418381691,
                "Left": 0.9009459018707275,
                "Top": 0.41939887404441833,
                "Width": 0.06394555419683456
            },
            "Polygon": [
                {
                    "X": 0.9009568095207214,
                    "Y": 0.41954505443573
                },
                {
                    "X": 0.9648914933204651,
                    "Y": 0.41939887404441833
                },
                {
                    "X": 0.9648795127868652,
                    "Y": 0.44210195541381836
                },
                {
                    "X": 0.9009459018707275,
                    "Y": 0.44224682450294495
                }
            ]
        },
        "Id": "4a3b66d2-8884-444c-8b5f-a2df4bb4e6c7",
        "Text": "14%",
        "TextType": "PRINTED"
    },
    {
        "BlockType": "WORD",
        "Confidence": 99.95044708251953,
        "Geometry": {
            "BoundingBox": {
                "Height": 0.021519336849451065,
                "Left": 0.040748003870248795,
                "Top": 0.4871576428413391,
                "Width": 0.040342047810554504
            },
            "Polygon": [
                {
                    "X": 0.040748003870248795,
                    "Y": 0.4872474670410156
                },
                {
                    "X": 0.08108748495578766,
                    "Y": 0.4871576428413391
                },
                {
                    "X": 0.081090047955513,
                    "Y": 0.5085879564285278
                },
                {
                    "X": 0.04075120389461517,
                    "Y": 0.5086770057678223
                }
            ]
        },
        "Id": "47c5c4f2-e342-4328-90e7-2761cdcf15be",
        "Text": "DK",
        "TextType": "PRINTED"
    },
    {
        "BlockType": "WORD",
        "Confidence": 99.91349792480469,
        "Geometry": {
            "BoundingBox": {
                "Height": 0.022693080827593803,
                "Left": 0.9006170034408569,
                "Top": 0.4872561991214752,
                "Width": 0.06411666423082352
            },
            "Polygon": [
                {
                    "X": 0.900627851486206,
                    "Y": 0.48739880323410034
                },
                {
                    "X": 0.9647336602210999,
                    "Y": 0.4872561991214752
                },
                {
                    "X": 0.9647217988967896,
                    "Y": 0.5098080039024353
                },
                {
                    "X": 0.9006170034408569,
                    "Y": 0.509949266910553
                }
            ]
        },
        "Id": "1d90873c-4d5c-4c41-989e-5e921198b3c0",
        "Text": "12%",
        "TextType": "PRINTED"
    },
    {
        "BlockType": "WORD",
        "Confidence": 99.97563934326172,
        "Geometry": {
            "BoundingBox": {
                "Height": 0.022064663469791412,
                "Left": 0.04104761779308319,
                "Top": 0.5547930002212524,
                "Width": 0.07316429167985916
            },
            "Polygon": [
                {
                    "X": 0.04104761779308319,
                    "Y": 0.5549513101577759
                },
                {
                    "X": 0.11420981585979462,
                    "Y": 0.5547930002212524
                },
                {
                    "X": 0.11421190947294235,
                    "Y": 0.5767008066177368
                },
                {
                    "X": 0.04105088487267494,
                    "Y": 0.5768576264381409
                }
            ]
        },
        "Id": "5bf07e13-8edb-45bb-8187-4779b290659e",
        "Text": "FRED",
        "TextType": "PRINTED"
    },
    {
        "BlockType": "WORD",
        "Confidence": 99.97491455078125,
        "Geometry": {
            "BoundingBox": {
                "Height": 0.023219842463731766,
                "Left": 0.9009563326835632,
                "Top": 0.5544626116752625,
                "Width": 0.06372009217739105
            },
            "Polygon": [
                {
                    "X": 0.9009674191474915,
                    "Y": 0.5546003580093384
                },
                {
                    "X": 0.9646764397621155,
                    "Y": 0.5544626116752625
                },
                {
                    "X": 0.9646642804145813,
                    "Y": 0.5775460004806519
                },
                {
                    "X": 0.9009563326835632,
                    "Y": 0.5776824355125427
                }
            ]
        },
        "Id": "355969b0-4cf9-434c-9a5d-4f3bad29f11e",
        "Text": "10%",
        "TextType": "PRINTED"
    },
    {
        "BlockType": "WORD",
        "Confidence": 99.9441146850586,
        "Geometry": {
            "BoundingBox": {
                "Height": 0.02231493592262268,
                "Left": 0.04025565832853317,
                "Top": 0.6223545074462891,
                "Width": 0.07157742977142334
            },
            "Polygon": [
                {
                    "X": 0.04025565832853317,
                    "Y": 0.6225049495697021
                },
                {
                    "X": 0.111830934882164,
                    "Y": 0.6223545074462891
                },
                {
                    "X": 0.11183308809995651,
                    "Y": 0.6445204019546509
                },
                {
                    "X": 0.0402589775621891,
                    "Y": 0.6446694135665894
                }
            ]
        },
        "Id": "ed8c9d88-2733-47bd-84f3-847a025e6374",
        "Text": "LULU",
        "TextType": "PRINTED"
    },
    {
        "BlockType": "WORD",
        "Confidence": 99.9078140258789,
        "Geometry": {
            "BoundingBox": {
                "Height": 0.023816082626581192,
                "Left": 0.9175830483436584,
                "Top": 0.621654212474823,
                "Width": 0.048026397824287415
            },
            "Polygon": [
                {
                    "X": 0.9175947308540344,
                    "Y": 0.6217551231384277
                },
                {
                    "X": 0.9656094312667847,
                    "Y": 0.621654212474823
                },
                {
                    "X": 0.9655969142913818,
                    "Y": 0.6453704833984375
                },
                {
                    "X": 0.9175830483436584,
                    "Y": 0.6454703211784363
                }
            ]
        },
        "Id": "406ca1e3-a0e4-4030-a29a-c02fce542beb",
        "Text": "9%",
        "TextType": "PRINTED"
    },
    {
        "BlockType": "WORD",
        "Confidence": 99.94876861572266,
        "Geometry": {
            "BoundingBox": {
                "Height": 0.023442856967449188,
                "Left": 0.03989062085747719,
                "Top": 0.6891514658927917,
                "Width": 0.07530452311038971
            },
            "Polygon": [
                {
                    "X": 0.03989062085747719,
                    "Y": 0.6893051862716675
                },
                {
                    "X": 0.11519293487071991,
                    "Y": 0.6891514658927917
                },
                {
                    "X": 0.1151951402425766,
                    "Y": 0.7124422788619995
                },
                {
                    "X": 0.03989411145448685,
                    "Y": 0.7125943303108215
                }
            ]
        },
        "Id": "4a99d94e-6e55-4de3-bffc-389158869243",
        "Text": "NEAL",
        "TextType": "PRINTED"
    },
    {
        "BlockType": "WORD",
        "Confidence": 99.87632751464844,
        "Geometry": {
            "BoundingBox": {
                "Height": 0.023502489551901817,
                "Left": 0.915650486946106,
                "Top": 0.6899284720420837,
                "Width": 0.04817110300064087
            },
            "Polygon": [
                {
                    "X": 0.9156619906425476,
                    "Y": 0.6900266408920288
                },
                {
                    "X": 0.9638215899467468,
                    "Y": 0.6899284720420837
                },
                {
                    "X": 0.9638092517852783,
                    "Y": 0.713333785533905
                },
                {
                    "X": 0.915650486946106,
                    "Y": 0.7134309411048889
                }
            ]
        },
        "Id": "53701db6-46e9-4d97-93d8-ea160e1e9eba",
        "Text": "6%",
        "TextType": "PRINTED"
    },
    {
        "BlockType": "WORD",
        "Confidence": 99.84471893310547,
        "Geometry": {
            "BoundingBox": {
                "Height": 0.023483803495764732,
                "Left": 0.040284089744091034,
                "Top": 0.7569553256034851,
                "Width": 0.08713126927614212
            },
            "Polygon": [
                {
                    "X": 0.040284089744091034,
                    "Y": 0.7571277618408203
                },
                {
                    "X": 0.12741336226463318,
                    "Y": 0.7569553256034851
                },
                {
                    "X": 0.12741535902023315,
                    "Y": 0.7802686095237732
                },
                {
                    "X": 0.04028758034110069,
                    "Y": 0.7804391384124756
                }
            ]
        },
        "Id": "be83142f-e979-4920-b2d5-4f8e2e4fdf48",
        "Text": "NIKOS",
        "TextType": "PRINTED"
    },
    {
        "BlockType": "WORD",
        "Confidence": 99.71063995361328,
        "Geometry": {
            "BoundingBox": {
                "Height": 0.02298501878976822,
                "Left": 0.9171431064605713,
                "Top": 0.7571859359741211,
                "Width": 0.04866519942879677
            },
            "Polygon": [
                {
                    "X": 0.9171543717384338,
                    "Y": 0.7572821378707886
                },
                {
                    "X": 0.9658082723617554,
                    "Y": 0.7571859359741211
                },
                {
                    "X": 0.965796172618866,
                    "Y": 0.7800757884979248
                },
                {
                    "X": 0.9171431064605713,
                    "Y": 0.7801709771156311
                }
            ]
        },
        "Id": "d69373bb-3824-4d6d-b546-40d3d40dec2d",
        "Text": "4%",
        "TextType": "PRINTED"
    },
    {
        "BlockType": "WORD",
        "Confidence": 20.346712112426758,
        "Geometry": {
            "BoundingBox": {
                "Height": 0.046435922384262085,
                "Left": 0.9817333817481995,
                "Top": 0.769607424736023,
                "Width": 0.018071450293064117
            },
            "Polygon": [
                {
                    "X": 0.9817584156990051,
                    "Y": 0.7696428894996643
                },
                {
                    "X": 0.9998047947883606,
                    "Y": 0.769607424736023
                },
                {
                    "X": 0.9997791647911072,
                    "Y": 0.8160086274147034
                },
                {
                    "X": 0.9817333817481995,
                    "Y": 0.8160433173179626
                }
            ]
        },
        "Id": "87f101ce-d870-4508-8965-5dad46466be7",
        "Text": "1",
        "TextType": "PRINTED"
    },
    {
        "BlockType": "WORD",
        "Confidence": 23.694299697875977,
        "Geometry": {
            "BoundingBox": {
                "Height": 0.022322269156575203,
                "Left": 0.9827743768692017,
                "Top": 0.8711729049682617,
                "Width": 0.01722564548254013
            },
            "Polygon": [
                {
                    "X": 0.9827864170074463,
                    "Y": 0.8712056279182434
                },
                {
                    "X": 1,
                    "Y": 0.8711729049682617
                },
                {
                    "X": 1,
                    "Y": 0.8934627771377563
                },
                {
                    "X": 0.9827743768692017,
                    "Y": 0.8934951424598694
                }
            ]
        },
        "Id": "53d4e1d5-9c1b-4509-a7cf-b766e26a9dfc",
        "Text": "las",
        "TextType": "PRINTED"
    }
]